geteventforhumans/LICENSE.txt
geteventforhumans/README.MD
geteventforhumans/__init__.py
geteventforhumans/parsekeyevents.py
geteventforhumans/requirements.txt
geteventforhumans/thirdparty.json
geteventforhumans-0.10.dist-info/LICENSE.rst
geteventforhumans-0.10.dist-info/METADATA
geteventforhumans-0.10.dist-info/WHEEL
geteventforhumans-0.10.dist-info/top_level.txt
geteventforhumans-0.10.dist-info/RECORD
