Metadata-Version: 2.1
Name: geteventforhumans
Version: 0.10
Summary: Android getevent for Humans!
Home-page: https://github.com/hansalemaos/geteventforhumans
Author: Johannes Fischer
Author-email: aulasparticularesdealemaosp@gmail.com
License: MIT
Keywords: android,adb
Classifier: Development Status :: 4 - Beta
Classifier: Programming Language :: Python :: 3 :: Only
Classifier: Programming Language :: Python :: 3.10
Classifier: Topic :: Software Development :: Libraries :: Python Modules
Classifier: Topic :: Utilities
License-File: LICENSE.rst
Requires-Dist: adbshellexecuter
